Workbook
Name F0_in: Inputs!$B$6
Name FC_AMT: Inputs!$B$4
Name K_CALL: Inputs!$B$10
Name K_PUT: Inputs!$B$9
Name PREM_CALL: Inputs!$B$12
Name PREM_PUT: Inputs!$B$11
Name R_FC: Inputs!$B$8
Name R_USD: Inputs!$B$7
Name S0_in: Inputs!$B$5
Name T_DAYS: Inputs!$B$13

Sheet Cover
A1: FX Transaction Hedge Model | B1: FX Transaction Hedge Model | C1: FX Transaction Hedge Model | D1: FX Transaction Hedge Model | E1: FX Transaction Hedge Model | F1: FX Transaction Hedge Model | G1: FX Transaction Hedge Model | H1: FX Transaction Hedge Model
A3: Scenario 1 — U.S. Solar Equipment Importer | EUR 4,500,000 Receivable
A5: Prepared by | B5: Achilles Del Rosario
A6: Settlement date | B6: 2027-08-13
A7: Rate convention | B7: USD per EUR; ACT/360 simple interest
A8: Indicative forward | B8: =F0_in -> 1.0875
A9: Model status | B9: =Checks!F10 -> OK
A10: Purpose | B10: Compare USD proceeds from forward, money-market, and put hedges
A12: Formula-Driven Summary (Settlement-Date USD Proceeds)
A14: Forward Hedge | B14: Money-Market Hedge | C14: Put Hedge at Spot | D14: Put Floor
A15: =Forward_Calc!B6 -> 4893750 | B15: =Money_Market_Calc!C6 -> 4893869 | C15: =Option_Calc!B6 -> 4837500 | D15: =Option_Calc!B8 -> 4837500
A17: Use the Inputs tab to replace all indicative placeholders with live market data. Gray cells are formula-driven outputs. See Checks for the parity, repayment, option-continuity, and sensitivity-grid audit checklist.

Sheet Legend_Key
A1: Legend / Key | B1: Legend / Key | C1: Legend / Key | D1: Legend / Key | E1: Legend / Key
A3: Cell convention | B3: Appearance | C3: Meaning
A4: Editable input | B4: Yellow fill / blue text | C4: Indicative placeholder; replace at Stage 4
A5: Formula / calculation | B5: White fill / black text | C5: Calculated from named ranges or linked formulas
A6: Cross-sheet link | B6: White fill / green text | C6: Formula references another workbook tab
A7: Output | B7: Gray fill / black bold text | C7: Formula-driven summary result
A9: All rates are USD per EUR. A decline in EURUSD is adverse to this EUR receivable. Money-market calculations use ACT/360 simple interest. The model excludes transaction costs, taxes, hedge accounting, credit risk, collateral, and premium financing.

Sheet Inputs
A1: Inputs — Scenario 1: U.S. Solar Equipment Importer | B1: Inputs — Scenario 1: U.S. Solar Equipment Importer | C1: Inputs — Scenario 1: U.S. Solar Equipment Importer | D1: Inputs — Scenario 1: U.S. Solar Equipment Importer | E1: Inputs — Scenario 1: U.S. Solar Equipment Importer | F1: Inputs — Scenario 1: U.S. Solar Equipment Importer
A3: Named Range | B3: Indicative Placeholder | C3: Unit / Basis | D3: Stage 4 Source | E3: Status | F3: Notes
A4: FC_AMT | B4: 4500000 | C4: EUR | D4: Receivables contract / ledger | E4: Indicative | F4: Foreign-currency receivable
A5: S0_in | B5: 1.1 | C5: USD per EUR | D5: ECB EUR exchange-rate reference | E5: Indicative | F5: Spot at inception
A6: F0_in | B6: 1.0875 | C6: USD per EUR | D6: Assigned scenario; Stage 4: executable bank/dealer quote | E6: Indicative | F6: One-year EURUSD forward
A7: R_USD | B7: 0.0425 | C7: Annual %, ACT/360 | D7: U.S. Treasury 1-year yield or USD money-market rate | E7: Indicative | F7: USD simple-interest rate
A8: R_FC | B8: 0.0543 | C8: Annual %, ACT/360 | D8: ECB euro-area money-market / EUR deposit rate | E8: Indicative | F8: Parity-consistent placeholder
A9: K_PUT | B9: 1.1 | C9: USD per EUR | D9: OTC dealer strike | E9: Indicative | F9: Put strike, at/near spot
A10: K_CALL | B10: 1.1 | C10: USD per EUR | D10: OTC dealer strike | E10: Indicative | F10: Standard-contract input; unused for receivable
A11: PREM_PUT | B11: 0.025 | C11: USD per EUR | D11: OTC EUR put premium | E11: Indicative | F11: Premium paid at inception
A12: PREM_CALL | B12: 0.025 | C12: USD per EUR | D12: OTC EUR call premium | E12: Indicative | F12: Standard-contract input; unused for receivable
A13: T_DAYS | B13: 365 | C13: Days | D13: 2026-08-13 to 2027-08-13 | E13: Indicative | F13: Settlement horizon
A15: All yellow/blue cells are editable placeholders and must be replaced with live, sourced market data at Stage 4. All downstream outputs are formulas.

Sheet Forward_Calc
A1: Forward Hedge Calculation | B1: Forward Hedge Calculation | C1: Forward Hedge Calculation | D1: Forward Hedge Calculation
A3: Calculation | B3: USD Proceeds
A4: Foreign-currency receivable (EUR) | B4: =FC_AMT -> 4500000
A5: Forward rate (USD/EUR) | B5: =F0_in -> 1.0875
A6: USD_FWD | B6: =FC_AMT*F0_in -> 4893750
A8: Forward hedge locks the settlement-date USD proceeds at FC_AMT × F0_in. It is invariant across the sensitivity grid.

Sheet Money_Market_Calc
A1: Money-Market Hedge Calculation | B1: Money-Market Hedge Calculation | C1: Money-Market Hedge Calculation | D1: Money-Market Hedge Calculation | E1: Money-Market Hedge Calculation
A3: Step | B3: Formula logic | C3: Value
A4: 1 | B4: FC_BORROW = FC_AMT / (1 + R_FC × T_DAYS/360) | C4: =FC_AMT/(1+R_FC*T_DAYS/360) -> 4265183.9
A5: 2 | B5: USD_NOW = FC_BORROW × S0_in | C5: =C4*S0_in -> 4691702.2
A6: 3 | B6: USD_MM = USD_NOW × (1 + R_USD × T_DAYS/360) | C6: =C5*(1+R_USD*T_DAYS/360) -> 4893869
B8: F_IMPLIED = S0_in × (1 + R_USD × T_DAYS/360) / (1 + R_FC × T_DAYS/360) | C8: =S0_in*(1+R_USD*T_DAYS/360)/(1+R_FC*T_DAYS/360) -> 1.0875264
B9: Parity delta: F_IMPLIED − F0_in | C9: =C8-F0_in -> 2.6443482e-05
B10: USD_MM − USD_FWD | C10: =C6-Forward_Calc!B6 -> 118.99567
A12: At settlement, the EUR receivable repays the FC borrowing and interest exactly. USD_MM is the locked USD proceed. The parity check compares F_IMPLIED with F0_in and USD_MM with USD_FWD.

Sheet Option_Calc
A1: Put Option Hedge Calculation | B1: Put Option Hedge Calculation | C1: Put Option Hedge Calculation | D1: Put Option Hedge Calculation
A3: Calculation | B3: Value
A4: Put premium paid today | B4: =FC_AMT*PREM_PUT -> 112500
A5: Base-case settlement spot (S0_in) | B5: =S0_in -> 1.1
A6: USD_PUT at S0_in | B6: =FC_AMT*MAX(S0_in,K_PUT)-FC_AMT*PREM_PUT -> 4837500
A7: Lowest sensitivity spot | B7: =MIN(Sensitivity!A5:A15) -> 1.045
A8: USD_FLOOR_PUT | B8: =MIN(Sensitivity!E5:E15) -> 4837500
A9: Option payoff rule | B9: =MAX(B5,K_PUT)*FC_AMT-FC_AMT*PREM_PUT -> 4837500
A11: The put establishes a floor at K_PUT less the premium: USD_PUT(S_T) = FC_AMT × MAX(S_T, K_PUT) − FC_AMT × PREM_PUT. It participates in EUR appreciation above the strike.

Sheet Sensitivity
A1: Sensitivity — Settlement Spot ±5% | B1: Sensitivity — Settlement Spot ±5% | C1: Sensitivity — Settlement Spot ±5% | D1: Sensitivity — Settlement Spot ±5% | E1: Sensitivity — Settlement Spot ±5% | F1: Sensitivity — Settlement Spot ±5% | G1: Sensitivity — Settlement Spot ±5% | H1: Sensitivity — Settlement Spot ±5% | I1: Sensitivity — Settlement Spot ±5% | J1: Sensitivity — Settlement Spot ±5%
A3: S_T (USD/EUR) | B3: USD_NO_HEDGE | C3: USD_FWD | D3: USD_MM | E3: USD_PUT | G3: CFO takeaway
G4: The unhedged outcome moves one-for-one with EURUSD. The forward and money-market strategies provide fixed USD proceeds. The put preserves a downside floor while retaining upside when EURUSD rises above K_PUT.
A5: =S0_in*(1+-5*1%) -> 1.045 | B5: =A5*FC_AMT -> 4702500 | C5: =Forward_Calc!B6 -> 4893750 | D5: =Money_Market_Calc!C6 -> 4893869 | E5: =FC_AMT*MAX(A5,K_PUT)-FC_AMT*PREM_PUT -> 4837500
A6: =S0_in*(1+-4*1%) -> 1.056 | B6: =A6*FC_AMT -> 4752000 | C6: =Forward_Calc!B6 -> 4893750 | D6: =Money_Market_Calc!C6 -> 4893869 | E6: =FC_AMT*MAX(A6,K_PUT)-FC_AMT*PREM_PUT -> 4837500
A7: =S0_in*(1+-3*1%) -> 1.067 | B7: =A7*FC_AMT -> 4801500 | C7: =Forward_Calc!B6 -> 4893750 | D7: =Money_Market_Calc!C6 -> 4893869 | E7: =FC_AMT*MAX(A7,K_PUT)-FC_AMT*PREM_PUT -> 4837500
A8: =S0_in*(1+-2*1%) -> 1.078 | B8: =A8*FC_AMT -> 4851000 | C8: =Forward_Calc!B6 -> 4893750 | D8: =Money_Market_Calc!C6 -> 4893869 | E8: =FC_AMT*MAX(A8,K_PUT)-FC_AMT*PREM_PUT -> 4837500
A9: =S0_in*(1+-1*1%) -> 1.089 | B9: =A9*FC_AMT -> 4900500 | C9: =Forward_Calc!B6 -> 4893750 | D9: =Money_Market_Calc!C6 -> 4893869 | E9: =FC_AMT*MAX(A9,K_PUT)-FC_AMT*PREM_PUT -> 4837500
A10: =S0_in*(1+0*1%) -> 1.1 | B10: =A10*FC_AMT -> 4950000 | C10: =Forward_Calc!B6 -> 4893750 | D10: =Money_Market_Calc!C6 -> 4893869 | E10: =FC_AMT*MAX(A10,K_PUT)-FC_AMT*PREM_PUT -> 4837500
A11: =S0_in*(1+1*1%) -> 1.111 | B11: =A11*FC_AMT -> 4999500 | C11: =Forward_Calc!B6 -> 4893750 | D11: =Money_Market_Calc!C6 -> 4893869 | E11: =FC_AMT*MAX(A11,K_PUT)-FC_AMT*PREM_PUT -> 4887000
A12: =S0_in*(1+2*1%) -> 1.122 | B12: =A12*FC_AMT -> 5049000 | C12: =Forward_Calc!B6 -> 4893750 | D12: =Money_Market_Calc!C6 -> 4893869 | E12: =FC_AMT*MAX(A12,K_PUT)-FC_AMT*PREM_PUT -> 4936500
A13: =S0_in*(1+3*1%) -> 1.133 | B13: =A13*FC_AMT -> 5098500 | C13: =Forward_Calc!B6 -> 4893750 | D13: =Money_Market_Calc!C6 -> 4893869 | E13: =FC_AMT*MAX(A13,K_PUT)-FC_AMT*PREM_PUT -> 4986000
A14: =S0_in*(1+4*1%) -> 1.144 | B14: =A14*FC_AMT -> 5148000 | C14: =Forward_Calc!B6 -> 4893750 | D14: =Money_Market_Calc!C6 -> 4893869 | E14: =FC_AMT*MAX(A14,K_PUT)-FC_AMT*PREM_PUT -> 5035500
A15: =S0_in*(1+5*1%) -> 1.155 | B15: =A15*FC_AMT -> 5197500 | C15: =Forward_Calc!B6 -> 4893750 | D15: =Money_Market_Calc!C6 -> 4893869 | E15: =FC_AMT*MAX(A15,K_PUT)-FC_AMT*PREM_PUT -> 5085000

Sheet Checks
A1: Validation Checks | B1: Validation Checks | C1: Validation Checks | D1: Validation Checks | E1: Validation Checks | F1: Validation Checks | G1: Validation Checks
A3: Check | B3: Actual | C3: Expected | D3: Difference | E3: Tolerance | F3: Status | G3: Notes
A4: Forward parity: F_IMPLIED ≈ F0_in | B4: =Money_Market_Calc!C8 -> 1.0875264 | C4: =F0_in -> 1.0875 | D4: =B4-C4 -> 2.6443482e-05 | E4: =0.0001 -> 0.0001 | F4: =IF(ABS(D4)<=E4,"OK","CHECK") -> OK | G4: USD/EUR
A5: MM proceeds ≈ forward proceeds | B5: =Money_Market_Calc!C6 -> 4893869 | C5: =Forward_Calc!B6 -> 4893750 | D5: =B5-C5 -> 118.99567 | E5: =500 -> 500 | F5: =IF(ABS(D5)<=E5,"OK","CHECK") -> OK | G5: USD
A6: FC borrowing repays receivable | B6: =Money_Market_Calc!C4*(1+R_FC*T_DAYS/360) -> 4500000 | C6: =FC_AMT -> 4500000 | D6: =B6-C6 -> 0 | E6: =0.01 -> 0.01 | F6: =IF(ABS(D6)<=E6,"OK","CHECK") -> OK | G6: EUR
A7: Put continuity at strike | B7: =FC_AMT*MAX(K_PUT,K_PUT)-FC_AMT*PREM_PUT -> 4837500 | C7: =FC_AMT*K_PUT-FC_AMT*PREM_PUT -> 4837500 | D7: =B7-C7 -> 0 | E7: =0.01 -> 0.01 | F7: =IF(ABS(D7)<=E7,"OK","CHECK") -> OK | G7: USD at strike
A8: Sensitivity grid: 11 rows | B8: =COUNT(Sensitivity!A5:A15) -> 11 | C8: =11 -> 11 | D8: =B8-C8 -> 0 | E8: =0 -> 0 | F8: =IF(D8=0,"OK","CHECK") -> OK | G8: Required 11 scenarios
A9: Sensitivity grid contains S0_in | B9: =COUNTIF(Sensitivity!A5:A15,S0_in) -> 1 | C9: =1 -> 1 | D9: =B9-C9 -> 0 | E9: =0 -> 0 | F9: =IF(D9=0,"OK","CHECK") -> OK | G9: Baseline included
A10: Overall Model Status | F10: =IF(COUNTIF(F4:F9,"OK")=6,"OK","CHECK") -> OK

Sheet Notes_Assumptions
A1: Notes & Assumptions | B1: Notes & Assumptions | C1: Notes & Assumptions | D1: Notes & Assumptions | E1: Notes & Assumptions | F1: Notes & Assumptions
A3: Topic | B3: Specification
A4: Scenario | B4: Scenario 1 — U.S. Solar Equipment Importer; EUR 4,500,000 receivable
A5: Settlement | B5: 2027-08-13; T_DAYS = 365
A6: Quote convention | B6: USD per EUR; lower EURUSD is adverse to the receivable
A7: Rate basis | B7: ACT/360 simple interest for both legs
A8: Premium treatment | B8: USD premium paid at inception; deducted from reported settlement proceeds without financing
A9: Excluded items | B9: Transaction costs, bid-ask, taxes, hedge accounting, credit risk, collateral, and premium financing
A10: Stage 4 data protocol | B10: Replace all yellow/blue inputs with live, sourced values and record access timestamps
